fbilr/__init__.py
fbilr/finders.py
fbilr/reader.py
fbilr/utils.py
fbilr-1.2.0.data/scripts/fbilr
fbilr-1.2.0.data/scripts/plot_barcode_detail.py
fbilr-1.2.0.data/scripts/split_reads.py
fbilr-1.2.0.dist-info/LICENSE
fbilr-1.2.0.dist-info/METADATA
fbilr-1.2.0.dist-info/WHEEL
fbilr-1.2.0.dist-info/top_level.txt
fbilr-1.2.0.dist-info/RECORD
