Metadata-Version: 2.1
Name: fbilr
Version: 1.2.0
Summary: Find barcode in long reads
Home-page: https://github.com/Ckenen/fbilr
Author: Zonggui Chen
Author-email: ggchenzonggui@qq.com
License: UNKNOWN
Platform: UNKNOWN
Classifier: Programming Language :: Python :: 3
Classifier: License :: OSI Approved :: MIT License
Classifier: Operating System :: Unix
Requires-Python: >=3.6
License-File: LICENSE
Requires-Dist: edlib
Requires-Dist: biopython
Requires-Dist: numpy
Requires-Dist: matplotlib
Requires-Dist: pygz
